CHANGES.txt
LICENSE.txt
MANIFEST.in
README.txt
RELEASE-VERSION
git_version.py
setup.cfg
setup.py
doc/.DS_Store
doc/Makefile
doc/source/Gallery.png
doc/source/Gallery.svg
doc/source/conf.py
doc/source/examples.rst
doc/source/index.rst
doc/source/output.gds
doc/source/userguide.rst
doc/source/versions.rst
doc/source/_themes/sphinx13/layout.html
doc/source/_themes/sphinx13/theme.conf
doc/source/_themes/sphinx13/static/.DS_Store
doc/source/_themes/sphinx13/static/HeaderLogo.ai
doc/source/_themes/sphinx13/static/bodybg.png
doc/source/_themes/sphinx13/static/footerbg.png
doc/source/_themes/sphinx13/static/gdsCAD_header.png
doc/source/_themes/sphinx13/static/headerbg.png
doc/source/_themes/sphinx13/static/listitem.png
doc/source/_themes/sphinx13/static/relbg.png
doc/source/_themes/sphinx13/static/sphinx13.css
doc/source/_themes/sphinx13/static/sphinxheader.png
doc/source/api/api.rst
doc/source/api/core_api.rst
doc/source/api/shapes_api.rst
doc/source/api/templates_api.rst
doc/source/api/utils_api.rst
gdsCAD/__init__.py
gdsCAD/core.py
gdsCAD/font.py
gdsCAD/shapes.py
gdsCAD/templates.py
gdsCAD/utils.py
gdsCAD.egg-info/PKG-INFO
gdsCAD.egg-info/SOURCES.txt
gdsCAD.egg-info/dependency_links.txt
gdsCAD.egg-info/top_level.txt
gdsCAD/resources/ALIGNMENT.GDS
gdsCAD/resources/hershey/LICENSE
gdsCAD/resources/hershey/cyrilc.hmp
gdsCAD/resources/hershey/gothgbt.hmp
gdsCAD/resources/hershey/gothgrt.hmp
gdsCAD/resources/hershey/gothitt.hmp
gdsCAD/resources/hershey/greekc.hmp
gdsCAD/resources/hershey/greekcs.hmp
gdsCAD/resources/hershey/greekp.hmp
gdsCAD/resources/hershey/greeks.hmp
gdsCAD/resources/hershey/hershey
gdsCAD/resources/hershey/italicc.hmp
gdsCAD/resources/hershey/italiccs.hmp
gdsCAD/resources/hershey/italict.hmp
gdsCAD/resources/hershey/romanc.hmp
gdsCAD/resources/hershey/romancs.hmp
gdsCAD/resources/hershey/romand.hmp
gdsCAD/resources/hershey/romanp.hmp
gdsCAD/resources/hershey/romans.hmp
gdsCAD/resources/hershey/romant.hmp
gdsCAD/resources/hershey/scriptc.hmp
gdsCAD/resources/hershey/scripts.hmp