Metadata-Version: 1.1
Name: gdsCAD
Version: 0.3.4
Summary: A simple Python package for creating or reading GDSII layout files.
Home-page: https://github.com/hohlraum/gdsCAD
Author: Andrew G. Mark
Author-email: mark@is.mpg.de
License: GNU GPLv3
Platform: All
Classifier: Development Status :: 3 - Alpha
Classifier: Intended Audience :: Education
Classifier: Intended Audience :: Manufacturing
Classifier: Intended Audience :: Science/Research
Classifier: License :: OSI Approved :: GNU General Public License v3 (GPLv3)
Classifier: Operating System :: OS Independent
Classifier: Programming Language :: Python :: 2.7
Classifier: Topic :: Scientific/Engineering
Classifier: Topic :: Scientific/Engineering :: Electronic Design Automation (EDA)
